customermerge/Load.py
customermerge/__init__.py
customermerge/util.py
customermerge-1.1.2.dist-info/LICENSE.txt
customermerge-1.1.2.dist-info/METADATA
customermerge-1.1.2.dist-info/WHEEL
customermerge-1.1.2.dist-info/top_level.txt
customermerge-1.1.2.dist-info/RECORD
