Metadata-Version: 2.1
Name: customermerge
Version: 1.1.2
Summary: Merge dataset from customer data trigger
Author: Emeral Digital
Author-email: eduardo.martinez.2117@gmail.com
Keywords: python,bigquery,storage,bucket
Classifier: Intended Audience :: Developers
Classifier: Programming Language :: Python :: 3
Classifier: Operating System :: Unix
Classifier: Operating System :: MacOS :: MacOS X
Classifier: Operating System :: Microsoft :: Windows
License-File: LICENSE.txt
Requires-Dist: google-cloud-storage
Requires-Dist: google-cloud-bigquery
Requires-Dist: pytz
